descope_pulumi/__init__.py
descope_pulumi/_inputs.py
descope_pulumi/_utilities.py
descope_pulumi/outputs.py
descope_pulumi/project.py
descope_pulumi/provider.py
descope_pulumi/pulumi-plugin.json
descope_pulumi/py.typed
descope_pulumi/config/__init__.py
descope_pulumi/config/__init__.pyi
descope_pulumi/config/vars.py
descope_pulumi-0.3.4.dist-info/METADATA
descope_pulumi-0.3.4.dist-info/WHEEL
descope_pulumi-0.3.4.dist-info/top_level.txt
descope_pulumi-0.3.4.dist-info/RECORD
